<manifest alg="2" build="2017.0.2.363" opt="false" iceEnabled="true" iceMarkupVersion="2" iceEnabledOptions="link,responsive,cachebuster,textStyling" exportTarget="other" domain="breedlove.xyz" resolutions="1x" timestamp="1492491241480">
  <folder name="css">
    <file name="site_global.css" crc="4185517240"/>
    <file name="master_master.css" crc="466431453" ref="index"/>
    <file name="nomq_preview_master_master.css" crc="131192573" ref="index"/>
    <file name="index.css" crc="68854140" ref="index"/>
    <file name="nomq_index.css" crc="203572090" ref="index"/>
  </folder>
  <folder name="assets">
    <file name="c11.mp4" crc="3907173702" seo="true" mt="1477378375000"/>
    <file name="resume-james-breedlove.docx" crc="4110303430" seo="true" mt="1487797709000"/>
    <file name="resume-james-breedlove.pdf" crc="4107491790" seo="true" mt="1478928845000"/>
  </folder>
  <folder name="scripts">
    <file name="jquery-1.8.3.min.js" crc="209076791" ref="index"/>
    <file name="museutils.js" crc="4232573551" ref="index"/>
    <file name="whatinput.js" crc="86476730" ref="index"/>
    <file name="museconfig.js" crc="3849126041" ref="index"/>
    <file name="jquery.musepolyfill.bgsize.js" crc="3880853905" ref="index"/>
    <file name="jquery.watch.js" crc="3844535323" ref="index"/>
    <file name="webpro.js" crc="3770351119" ref="index"/>
    <file name="musewpslideshow.js" crc="4244742588" ref="index"/>
    <file name="jquery.museoverlay.js" crc="432750910" ref="index"/>
    <file name="touchswipe.js" crc="3912873526" ref="index"/>
    <file name="jquery.scrolleffects.js" crc="146279342" ref="index"/>
    <file name="jquery.museresponsive.js" crc="433634197" ref="index"/>
    <file name="require.js" crc="4234670167" ref="index"/>
  </folder>
  <folder name="images">
    <file name="logo png_00000.png" crc="275656833" ref="index">
      <caption webpage="index" alt=""/>
      <caption webpage="index" alt=""/>
    </file>
    <file name="logo png_00000-u13197.png" crc="4251987461" ref="index"/>
    <file name="profile pic.jpg" crc="101992226" ref="index">
      <caption webpage="index" alt=""/>
      <caption webpage="index" alt=""/>
      <caption webpage="index" alt=""/>
      <caption webpage="index" alt=""/>
      <caption webpage="index" alt=""/>
    </file>
    <file name="robot-u2160-fr.jpg" crc="358826833" ref="index"/>
    <file name="blank.gif" crc="4208392903" ref="index"/>
    <file name="firstoverview-3269237x157.jpg" crc="3842164583" seo="true" ref="index">
      <caption webpage="index" alt=""/>
      <caption webpage="index" alt=""/>
    </file>
    <file name="drone2-u2311-fr.jpg" crc="3995065409" ref="index"/>
    <file name="drone3.jpg" crc="141800337" seo="true" ref="index">
      <caption webpage="index" alt=""/>
      <caption webpage="index" alt=""/>
      <caption webpage="index" alt=""/>
      <caption webpage="index" alt=""/>
    </file>
    <file name="drone1-u2300-fr.jpg" crc="3978924133" ref="index"/>
    <file name="home depot1-u2407-fr.jpg" crc="395234695" ref="index"/>
    <file name="angular logo-u2487.png" crc="4156057531" ref="index"/>
    <file name="angular logo-u2487-r.png" crc="4185300615" ref="index"/>
    <file name="nativescript_logo-u2501.png" crc="475450627" ref="index"/>
    <file name="nativescript_logo-u2501-r.png" crc="80525314" ref="index"/>
    <file name="u2523.png" crc="458857624" ref="index"/>
    <file name="u2523-r.png" crc="103878069" ref="index"/>
    <file name="u2533.png" crc="36056481" ref="index"/>
    <file name="u2533-r.png" crc="3758784918" ref="index"/>
    <file name="home depot1-u2407-fr2.jpg" crc="471438239" ref="index"/>
    <file name="angular logo-u24872.png" crc="4156057531" ref="index"/>
    <file name="angular logo-u2487-r2.png" crc="4185300615" ref="index"/>
    <file name="nativescript_logo-u25012.png" crc="475450627" ref="index"/>
    <file name="nativescript_logo-u2501-r2.png" crc="80525314" ref="index"/>
    <file name="u25232.png" crc="458857624" ref="index"/>
    <file name="u2523-r2.png" crc="103878069" ref="index"/>
    <file name="u25332.png" crc="36056481" ref="index"/>
    <file name="u2533-r2.png" crc="3758784918" ref="index"/>
    <file name="firstoverview-3269272x181.jpg" crc="4136118742" seo="true" ref="index">
      <caption webpage="index" alt=""/>
    </file>
    <file name="robot-u2160-fr2.jpg" crc="471098293" ref="index"/>
    <file name="drone2-u2311-fr2.jpg" crc="3779466499" ref="index"/>
    <file name="drone1-u2300-fr2.jpg" crc="289198122" ref="index"/>
    <file name="home depot1-u2407-fr3.jpg" crc="3985262524" ref="index"/>
    <file name="nativescript_logo-u25013.png" crc="8037708" ref="index"/>
    <file name="nativescript_logo-u2501-r3.png" crc="169760294" ref="index"/>
    <file name="angular logo-u24873.png" crc="4227972060" ref="index"/>
    <file name="angular logo-u2487-r3.png" crc="452910426" ref="index"/>
    <file name="u25333.png" crc="84238775" ref="index"/>
    <file name="u2533-r3.png" crc="168482203" ref="index"/>
    <file name="u25233.png" crc="4199723409" ref="index"/>
    <file name="u2523-r3.png" crc="318655081" ref="index"/>
    <file name="firstoverview-3269260x173.jpg" crc="3944519223" seo="true" ref="index">
      <caption webpage="index" alt=""/>
    </file>
    <file name="drone2-u2311-fr3.jpg" crc="4130094424" ref="index"/>
    <file name="drone1-u2300-fr3.jpg" crc="418400024" ref="index"/>
    <file name="home depot1.jpg" crc="3972735565" ref="index">
      <caption webpage="index" alt=""/>
      <caption webpage="index" alt=""/>
    </file>
    <file name="angular logo-u24874.png" crc="375628377" ref="index"/>
    <file name="angular logo-u2487-r4.png" crc="255662887" ref="index"/>
    <file name="u25334.png" crc="3772061422" ref="index"/>
    <file name="u2533-r4.png" crc="515496922" ref="index"/>
    <file name="robot-u2160-fr3.jpg" crc="3794846272" ref="index"/>
    <file name="nativescript_logo-u25014.png" crc="315646554" ref="index"/>
    <file name="nativescript_logo-u2501-r4.png" crc="455531284" ref="index"/>
    <file name="u25234.png" crc="134348215" ref="index"/>
    <file name="u2523-r4.png" crc="3987454447" ref="index"/>
    <file name="robot.jpg" crc="231191047" ref="index">
      <caption webpage="index" alt=""/>
    </file>
    <file name="firstoverview-3269.jpg" crc="240875501" seo="true" ref="index">
      <caption webpage="index" alt=""/>
    </file>
    <file name="drone2.jpg" crc="29507663" ref="index">
      <caption webpage="index" alt=""/>
    </file>
    <file name="drone1.jpg" crc="321964161" ref="index">
      <caption webpage="index" alt=""/>
    </file>
    <file name="angular logo-u24875.png" crc="3919030034" ref="index"/>
    <file name="angular logo-u2487-r5.png" crc="4245453146" ref="index"/>
    <file name="u25235.png" crc="4091685828" ref="index"/>
    <file name="u2523-r5.png" crc="3919712574" ref="index"/>
    <file name="nativescript_logo-u25015.png" crc="4095380375" ref="index"/>
    <file name="nativescript_logo-u2501-r5.png" crc="3846341927" ref="index"/>
    <file name="u25335.png" crc="4093226876" ref="index"/>
    <file name="u2533-r5.png" crc="46331700" ref="index"/>
    <file name="pointer.png" crc="3760686964" seo="true" ref="index">
      <caption webpage="index" alt=""/>
      <caption webpage="index" alt=""/>
      <caption webpage="index" alt=""/>
      <caption webpage="index" alt=""/>
    </file>
    <file name="menu_icon_04_white_3line-crop-u30613.png" crc="4113681886" seo="true" ref="index">
      <caption webpage="index" alt=""/>
    </file>
    <file name="close_light.png" crc="126613487" seo="true" ref="index">
      <caption webpage="index" alt=""/>
    </file>
    <file name="emile-perron-190221 (1).jpg" crc="3877138646" ref="index">
      <caption webpage="index" alt=""/>
      <caption webpage="index" alt=""/>
      <caption webpage="index" alt=""/>
      <caption webpage="index" alt=""/>
      <caption webpage="index" alt=""/>
    </file>
  </folder>
  <file name="index.html" crc="3989233302" seo="true" mt="1492490605614" redirect="true"/>
</manifest>